utilitas/__init__.py
utilitas/admin.py
utilitas/apps.py
utilitas/exception_handler.py
utilitas/exceptions.py
utilitas/managers.py
utilitas/metadata.py
utilitas/middlewares.py
utilitas/migrations.py
utilitas/models.py
utilitas/pagination.py
utilitas/renderer.py
utilitas/serializers.py
utilitas/swagger_query_params.py
utilitas/swagger_serializers.py
utilitas/tests.py
utilitas/urls.py
utilitas/views.py
utilitas/migrations/__init__.py
django_utilitas-1.3.15.dist-info/LICENSE
django_utilitas-1.3.15.dist-info/METADATA
django_utilitas-1.3.15.dist-info/WHEEL
django_utilitas-1.3.15.dist-info/top_level.txt
django_utilitas-1.3.15.dist-info/RECORD
