Metadata-Version: 2.1
Name: django-utilitas
Version: 1.3.15
Summary: Django package with useful utility classes
Home-page: https://github.com/ninnroot/utilitas
Requires-Python: >=3.7
License-File: LICENSE
Requires-Dist: Django (>=4.0)
Requires-Dist: drf-yasg (>=1.21.4)
Requires-Dist: djangorestframework (>=3.14.0)
Requires-Dist: drf-flex-fields (>=1.0.0)
